{
"meta":{"test_sets":[],"test_metrics":[],"learn_metrics":[{"best_value":"Min","name":"RMSE"}],"launch_mode":"Train","parameters":"","iteration_count":100,"learn_sets":["learn"],"name":"experiment"},
"iterations":[
{"learn":[13.96962521],"iteration":0,"passed_time":0.0007396256441,"remaining_time":0.07322293876},
{"learn":[13.09082657],"iteration":1,"passed_time":0.001425144683,"remaining_time":0.06983208945},
{"learn":[12.27861651],"iteration":2,"passed_time":0.002541708431,"remaining_time":0.08218190595},
{"learn":[11.53029884],"iteration":3,"passed_time":0.003155644854,"remaining_time":0.07573547649},
{"learn":[10.87492512],"iteration":4,"passed_time":0.003778673699,"remaining_time":0.07179480027},
{"learn":[10.38155225],"iteration":5,"passed_time":0.00440199343,"remaining_time":0.06896456373},
{"learn":[9.857621344],"iteration":6,"passed_time":0.005382138006,"remaining_time":0.07150554779},
{"learn":[9.411181059],"iteration":7,"passed_time":0.006635090946,"remaining_time":0.07630354588},
{"learn":[8.998198398],"iteration":8,"passed_time":0.008084966304,"remaining_time":0.08174799263},
{"learn":[8.588034504],"iteration":9,"passed_time":0.008694262111,"remaining_time":0.078248359},
{"learn":[8.232135915],"iteration":10,"passed_time":0.009763234747,"remaining_time":0.07899344477},
{"learn":[7.936645968],"iteration":11,"passed_time":0.01066980833,"remaining_time":0.07824526109},
{"learn":[7.686327869],"iteration":12,"passed_time":0.01178065608,"remaining_time":0.07883977529},
{"learn":[7.453139483],"iteration":13,"passed_time":0.01244675784,"remaining_time":0.07645865532},
{"learn":[7.216574456],"iteration":14,"passed_time":0.01348665186,"remaining_time":0.07642436053},
{"learn":[7.018377399],"iteration":15,"passed_time":0.01463892465,"remaining_time":0.07685435439},
{"learn":[6.823313325],"iteration":16,"passed_time":0.01529822396,"remaining_time":0.07469132874},
{"learn":[6.666946823],"iteration":17,"passed_time":0.0160335866,"remaining_time":0.07304189453},
{"learn":[6.508910347],"iteration":18,"passed_time":0.01686338445,"remaining_time":0.07189127055},
{"learn":[6.386746007],"iteration":19,"passed_time":0.01736696296,"remaining_time":0.06946785183},
{"learn":[6.265973887],"iteration":20,"passed_time":0.01796550204,"remaining_time":0.06758450769},
{"learn":[6.169088554],"iteration":21,"passed_time":0.01850512223,"remaining_time":0.06560906974},
{"learn":[6.063254647],"iteration":22,"passed_time":0.01917012113,"remaining_time":0.06417823161},
{"learn":[5.976012341],"iteration":23,"passed_time":0.01986551959,"remaining_time":0.0629074787},
{"learn":[5.901135024],"iteration":24,"passed_time":0.02041420686,"remaining_time":0.06124262059},
{"learn":[5.835939901],"iteration":25,"passed_time":0.02126228913,"remaining_time":0.06051574599},
{"learn":[5.775227205],"iteration":26,"passed_time":0.02178832369,"remaining_time":0.05890917146},
{"learn":[5.723443194],"iteration":27,"passed_time":0.02241038351,"remaining_time":0.05762670046},
{"learn":[5.680032138],"iteration":28,"passed_time":0.02324482055,"remaining_time":0.05690973306},
{"learn":[5.627248312],"iteration":29,"passed_time":0.02372404207,"remaining_time":0.05535609816},
{"learn":[5.592690321],"iteration":30,"passed_time":0.02446353601,"remaining_time":0.05445109628},
{"learn":[5.544273978],"iteration":31,"passed_time":0.02519871913,"remaining_time":0.05354727814},
{"learn":[5.503344158],"iteration":32,"passed_time":0.02566441962,"remaining_time":0.05210654892},
{"learn":[5.478259921],"iteration":33,"passed_time":0.02630589314,"remaining_time":0.05106438081},
{"learn":[5.442185155],"iteration":34,"passed_time":0.02692459403,"remaining_time":0.05000281748},
{"learn":[5.407844279],"iteration":35,"passed_time":0.02769164899,"remaining_time":0.0492295982},
{"learn":[5.383507306],"iteration":36,"passed_time":0.02830697595,"remaining_time":0.04819836446},
{"learn":[5.362378839],"iteration":37,"passed_time":0.02889021193,"remaining_time":0.04713666157},
{"learn":[5.340630083],"iteration":38,"passed_time":0.02952463316,"remaining_time":0.04617955443},
{"learn":[5.318674311],"iteration":39,"passed_time":0.0301712013,"remaining_time":0.04525680195},
{"learn":[5.302066897],"iteration":40,"passed_time":0.03074309022,"remaining_time":0.04424005666},
{"learn":[5.284928558],"iteration":41,"passed_time":0.03127737666,"remaining_time":0.04319256777},
{"learn":[5.272330995],"iteration":42,"passed_time":0.03190798532,"remaining_time":0.04229663171},
{"learn":[5.261014227],"iteration":43,"passed_time":0.03225051927,"remaining_time":0.04104611544},
{"learn":[5.229469639],"iteration":44,"passed_time":0.03285540111,"remaining_time":0.04015660135},
{"learn":[5.215020572],"iteration":45,"passed_time":0.03341977981,"remaining_time":0.03923191543},
{"learn":[5.193062414],"iteration":46,"passed_time":0.03393602596,"remaining_time":0.03826828459},
{"learn":[5.180484848],"iteration":47,"passed_time":0.03444855698,"remaining_time":0.03731927006},
{"learn":[5.165159502],"iteration":48,"passed_time":0.03504560059,"remaining_time":0.03647603327},
{"learn":[5.141982763],"iteration":49,"passed_time":0.03556093625,"remaining_time":0.03556093625},
{"learn":[5.131085119],"iteration":50,"passed_time":0.03607248753,"remaining_time":0.03465788018},
{"learn":[5.115896901],"iteration":51,"passed_time":0.03659150478,"remaining_time":0.03377677364},
{"learn":[5.102227813],"iteration":52,"passed_time":0.03713429509,"remaining_time":0.03293041263},
{"learn":[5.092694221],"iteration":53,"passed_time":0.03767742233,"remaining_time":0.03209558199},
{"learn":[5.084135611],"iteration":54,"passed_time":0.03819324947,"remaining_time":0.03124902229},
{"learn":[5.067392027],"iteration":55,"passed_time":0.03875262493,"remaining_time":0.03044849102},
{"learn":[5.05548496],"iteration":56,"passed_time":0.03931092394,"remaining_time":0.02965560929},
{"learn":[5.037754059],"iteration":57,"passed_time":0.03982265011,"remaining_time":0.02883709146},
{"learn":[5.018441657],"iteration":58,"passed_time":0.04040375602,"remaining_time":0.02807718638},
{"learn":[5.009952596],"iteration":59,"passed_time":0.04094525929,"remaining_time":0.02729683953},
{"learn":[5.000684433],"iteration":60,"passed_time":0.0415022163,"remaining_time":0.02653420386},
{"learn":[4.982819001],"iteration":61,"passed_time":0.0420537978,"remaining_time":0.02577490833},
{"learn":[4.966552282],"iteration":62,"passed_time":0.04260801869,"remaining_time":0.02502375701},
{"learn":[4.948387795],"iteration":63,"passed_time":0.04312340931,"remaining_time":0.02425691774},
{"learn":[4.933079332],"iteration":64,"passed_time":0.04379423271,"remaining_time":0.02358150992},
{"learn":[4.923067166],"iteration":65,"passed_time":0.04435574003,"remaining_time":0.02284992668},
{"learn":[4.91587203],"iteration":66,"passed_time":0.04490038523,"remaining_time":0.02211511512},
{"learn":[4.906625327],"iteration":67,"passed_time":0.04549148549,"remaining_time":0.02140775788},
{"learn":[4.895848666],"iteration":68,"passed_time":0.04609361122,"remaining_time":0.02070872388},
{"learn":[4.886562569],"iteration":69,"passed_time":0.04664189982,"remaining_time":0.01998938564},
{"learn":[4.876525557],"iteration":70,"passed_time":0.04726577634,"remaining_time":0.01930573963},
{"learn":[4.866771122],"iteration":71,"passed_time":0.04777508833,"remaining_time":0.01857920102},
{"learn":[4.860489381],"iteration":72,"passed_time":0.04839521082,"remaining_time":0.01789959852},
{"learn":[4.846895943],"iteration":73,"passed_time":0.04895710789,"remaining_time":0.01720114601},
{"learn":[4.830532583],"iteration":74,"passed_time":0.04947221298,"remaining_time":0.01649073766},
{"learn":[4.818616331],"iteration":75,"passed_time":0.04999528264,"remaining_time":0.01578798399},
{"learn":[4.806132466],"iteration":76,"passed_time":0.05054709507,"remaining_time":0.01509848294},
{"learn":[4.800479202],"iteration":77,"passed_time":0.05112868138,"remaining_time":0.01442091013},
{"learn":[4.797819002],"iteration":78,"passed_time":0.05144642469,"remaining_time":0.01367563188},
{"learn":[4.786614428],"iteration":79,"passed_time":0.05192537103,"remaining_time":0.01298134276},
{"learn":[4.777804595],"iteration":80,"passed_time":0.05241209706,"remaining_time":0.01229419561},
{"learn":[4.767203373],"iteration":81,"passed_time":0.05304350913,"remaining_time":0.01164369713},
{"learn":[4.752577047],"iteration":82,"passed_time":0.05356784085,"remaining_time":0.01097172644},
{"learn":[4.743678884],"iteration":83,"passed_time":0.05405137498,"remaining_time":0.0102955},
{"learn":[4.737404981],"iteration":84,"passed_time":0.05470048507,"remaining_time":0.009653026777},
{"learn":[4.728022428],"iteration":85,"passed_time":0.05531846963,"remaining_time":0.009005332265},
{"learn":[4.723347156],"iteration":86,"passed_time":0.05586029377,"remaining_time":0.008346940449},
{"learn":[4.717517757],"iteration":87,"passed_time":0.05641349852,"remaining_time":0.007692749799},
{"learn":[4.709503034],"iteration":88,"passed_time":0.05696528561,"remaining_time":0.007040653277},
{"learn":[4.703039995],"iteration":89,"passed_time":0.05749197832,"remaining_time":0.006387997591},
{"learn":[4.696059284],"iteration":90,"passed_time":0.05803022188,"remaining_time":0.005739252714},
{"learn":[4.686066202],"iteration":91,"passed_time":0.05858957165,"remaining_time":0.005094745361},
{"learn":[4.674543063],"iteration":92,"passed_time":0.0592125466,"remaining_time":0.004456858346},
{"learn":[4.671858724],"iteration":93,"passed_time":0.05973336734,"remaining_time":0.003812768128},
{"learn":[4.6586434],"iteration":94,"passed_time":0.06026240641,"remaining_time":0.003171705601},
{"learn":[4.650850795],"iteration":95,"passed_time":0.0607590215,"remaining_time":0.002531625896},
{"learn":[4.647951816],"iteration":96,"passed_time":0.06129994443,"remaining_time":0.00189587457},
{"learn":[4.636294688],"iteration":97,"passed_time":0.06179639926,"remaining_time":0.001261151005},
{"learn":[4.629521481],"iteration":98,"passed_time":0.06236102816,"remaining_time":0.0006299093753},
{"learn":[4.625948565],"iteration":99,"passed_time":0.0629013554,"remaining_time":0}
]}